suite/__init__.py
suite/analyzer.py
suite-1.0.1.dist-info/licenses/LICENSE
suite-1.0.1.dist-info/METADATA
suite-1.0.1.dist-info/WHEEL
suite-1.0.1.dist-info/top_level.txt
suite-1.0.1.dist-info/RECORD
