Metadata-Version: 2.4
Name: suite
Version: 1.0.1
Summary: Semantic Unit Testing
Author-email: Alex Molas <alexmolasmartin@gmail.com>
License: MIT
Project-URL: Homepage, https://github.com/alexmolas/suite
Project-URL: Bug Tracker, https://github.com/alexmolas/suite/issues
Classifier: Programming Language :: Python :: 3
Classifier: Programming Language :: Python :: 3.13
Classifier: License :: OSI Approved :: MIT License
Classifier: Operating System :: OS Independent
Requires-Python: >=3.13
License-File: LICENSE
Requires-Dist: dotenv>=0.9.9
Requires-Dist: llm>=0.12.0
Requires-Dist: llm-ollama>=0.9.1
Requires-Dist: llm-openrouter>=0.4
Requires-Dist: openai>=1.71.0
Requires-Dist: pydantic>=2.11.2
Requires-Dist: pytest>=7.0.0
Requires-Dist: ruff>=0.11.4
Dynamic: license-file
